fast_poisson_solver/__init__.py
fast_poisson_solver/analyze.py
fast_poisson_solver/data.py
fast_poisson_solver/data_utils/source_functions.py
fast_poisson_solver/diff_matrices.py
fast_poisson_solver/model.py
fast_poisson_solver/numeric_solver.py
fast_poisson_solver/plotter.py
fast_poisson_solver/resources/final.pt
fast_poisson_solver/resources/infos.yaml
fast_poisson_solver/solver.py
fast_poisson_solver/utils.py
LICENSE
pyproject.toml
README.md
fast_poisson_solver-0.1.14.dist-info/LICENSE
fast_poisson_solver-0.1.14.dist-info/METADATA
fast_poisson_solver-0.1.14.dist-info/WHEEL
fast_poisson_solver-0.1.14.dist-info/RECORD
