Metadata-Version: 2.1
Name: fast-poisson-solver
Version: 0.1.14
Summary: A fast solver for the Poisson equation.
Home-page: https://github.com/matthiasnwt/fast-poisson-solver
License: GNUv3
Keywords: Poisson,solver,fast,python
Author: Matthias Neuwirth
Requires-Python: >=3.8,<4.0
Classifier: Development Status :: 3 - Alpha
Classifier: Intended Audience :: Developers
Classifier: Intended Audience :: Education
Classifier: Intended Audience :: Science/Research
Classifier: License :: OSI Approved :: GNU General Public License v3 or later (GPLv3+)
Classifier: License :: Other/Proprietary License
Classifier: Natural Language :: English
Classifier: Operating System :: OS Independent
Classifier: Programming Language :: Python :: 3
Classifier: Programming Language :: Python :: 3.8
Classifier: Programming Language :: Python :: 3.9
Classifier: Programming Language :: Python :: 3.10
Classifier: Programming Language :: Python :: 3.11
Classifier: Programming Language :: Python :: 3
Classifier: Topic :: Scientific/Engineering :: Artificial Intelligence
Classifier: Topic :: Scientific/Engineering :: Mathematics
Classifier: Topic :: Scientific/Engineering :: Physics
Requires-Dist: PyYAML (>=6.0)
Requires-Dist: matplotlib (>=3)
Requires-Dist: numpy (>=1.14)
Requires-Dist: numpydoc
Requires-Dist: perlin_noise (>=1.12)
Requires-Dist: scikit-image (>=0.16)
Requires-Dist: scikit_learn (>=0.24)
Requires-Dist: scipy (>=1.7)
Requires-Dist: torch (>=1)
Project-URL: Documentation, https://fast-poisson-solver.readthedocs.io/en/latest/
Project-URL: Repository, https://github.com/matthiasnwt/fast-poisson-solver
